waveshare_ws170120_brightness/__init__.py
waveshare_ws170120_brightness-1.0.0.dist-info/LICENSE
waveshare_ws170120_brightness-1.0.0.dist-info/METADATA
waveshare_ws170120_brightness-1.0.0.dist-info/WHEEL
waveshare_ws170120_brightness-1.0.0.dist-info/entry_points.txt
waveshare_ws170120_brightness-1.0.0.dist-info/top_level.txt
waveshare_ws170120_brightness-1.0.0.dist-info/zip-safe
waveshare_ws170120_brightness-1.0.0.dist-info/RECORD
