Metadata-Version: 2.1
Name: waveshare-ws170120-brightness
Version: 1.0.0
Summary: Control the brightness of an Waveshare WS170120 touch-screen.
Author-email: Claus-Justus Heine <himself@claus-justus-heine.de>
License: GPL-3.0
Project-URL: Homepage, https://github.com/rotdrop/waveshare-ws170120-brightness
Platform: any
Requires-Python: >=3.10.0
License-File: LICENSE
Requires-Dist: hidraw-pure (==1.1)
